LICENSE
README.md
setup.py
HiveNetBuildTool/__init__.py
HiveNetBuildTool/build.py
HiveNetBuildTool.egg-info/PKG-INFO
HiveNetBuildTool.egg-info/SOURCES.txt
HiveNetBuildTool.egg-info/dependency_links.txt
HiveNetBuildTool.egg-info/not-zip-safe
HiveNetBuildTool.egg-info/requires.txt
HiveNetBuildTool.egg-info/top_level.txt
HiveNetBuildTool/plugins/__init__.py
HiveNetBuildTool/plugins/processer_dirs.py
HiveNetBuildTool/plugins/processer_get_sys_infos.py
HiveNetBuildTool/plugins/processer_print.py
HiveNetBuildTool/plugins/processer_prompt.py