Metadata-Version: 2.1
Name: HiveNetBuildTool
Version: 0.1.2
Summary: A universal code building tool.
Home-page: https://github.com/snakeclub/HiveNetAssemble/HiveNetBuildTool
Author: 黎慧剑
Author-email: snakeclub@163.com
Maintainer: 黎慧剑
Maintainer-email: snakeclub@163.com
License: Mozilla Public License 2.0
Keywords: HiveNetAssemble HiveNetBuildTool development python lib
Platform: all
Classifier: Operating System :: OS Independent
Classifier: License :: OSI Approved :: Mozilla Public License 2.0 (MPL 2.0)
Classifier: Programming Language :: Python :: 3.6
Classifier: Topic :: Software Development :: Libraries
License-File: LICENSE
